{
    "nodes": [
        {
            "proto_uri": "microservice/data_analyzer1.proto",
            "image": "file_based_energy_pipeline-data-analyzer:latest",
            "node_type": "MLModel",
            "container_name": "data_analyzer1",
            "operation_signature_list": [
                {
                    "connected_to": [
                        {
                            "container_name": "report_generator1",
                            "operation_signature": {
                                "operation_name": "GenerateReport"
                            }
                        }
                    ],
                    "operation_signature": {
                        "operation_name": "AnalyzeData",
                        "output_message_name": "AnalyzeDataResponse",
                        "input_message_name": "GenerateDataResponse",
                        "output_message_stream": false,
                        "input_message_stream": false
                    }
                }
            ]
        },
        {
            "proto_uri": "microservice/data_generator1.proto",
            "image": "file_based_energy_pipeline-data-generator:latest",
            "node_type": "MLModel",
            "container_name": "data_generator1",
            "operation_signature_list": [
                {
                    "connected_to": [
                        {
                            "container_name": "data_analyzer1",
                            "operation_signature": {
                                "operation_name": "AnalyzeData"
                            }
                        }
                    ],
                    "operation_signature": {
                        "operation_name": "GenerateData",
                        "output_message_name": "GenerateDataResponse",
                        "input_message_name": "GetConfigurationResponse",
                        "output_message_stream": false,
                        "input_message_stream": false
                    }
                }
            ]
        },
        {
            "proto_uri": "microservice/input_provider1.proto",
            "image": "file_based_energy_pipeline-input-provider:latest",
            "node_type": "DataSource",
            "container_name": "input_provider1",
            "operation_signature_list": [
                {
                    "connected_to": [
                        {
                            "container_name": "data_generator1",
                            "operation_signature": {
                                "operation_name": "GenerateData"
                            }
                        }
                    ],
                    "operation_signature": {
                        "operation_name": "GetConfiguration",
                        "output_message_name": "GetConfigurationResponse",
                        "input_message_name": "GetConfigurationRequest",
                        "output_message_stream": false,
                        "input_message_stream": false
                    }
                }
            ]
        },
        {
            "proto_uri": "microservice/report_generator1.proto",
            "image": "file_based_energy_pipeline-report-generator:latest",
            "node_type": "DataSink",
            "container_name": "report_generator1",
            "operation_signature_list": [
                {
                    "connected_to": [],
                    "operation_signature": {
                        "operation_name": "GenerateReport",
                        "output_message_name": "GenerateReportResponse",
                        "input_message_name": "AnalyzeDataResponse",
                        "output_message_stream": false,
                        "input_message_stream": false
                    }
                }
            ]
        }
    ],
    "name": "File Based Energy Pipeline",
    "pipeline_id": "0696224f-eb7d-41bf-8cd7-0464d82edb3c",
    "creation_date": "2026-02-25 01:55:50.342301",
    "type": "pipeline-topology/v2",
    "version": "2.0"
}